dataclay_common/__init__.py
dataclay_common/protos/__init__.py
dataclay_common/protos/common_messages_pb2.py
dataclay_common/protos/dataservice_messages_pb2.py
dataclay_common/protos/dataservice_pb2.py
dataclay_common/protos/dataservice_pb2_grpc.py
dataclay_common/protos/logicmodule_messages_pb2.py
dataclay_common/protos/logicmodule_pb2.py
dataclay_common/protos/logicmodule_pb2_grpc.py
dataclay_common/protos/metadata_service_pb2.py
dataclay_common/protos/metadata_service_pb2_grpc.py
dataClay_common-3.0.1671803325.dist-info/METADATA
dataClay_common-3.0.1671803325.dist-info/WHEEL
dataClay_common-3.0.1671803325.dist-info/top_level.txt
dataClay_common-3.0.1671803325.dist-info/RECORD
