Metadata-Version: 2.1
Name: dataClay-common
Version: 3.0.1671803325
Summary: Dataclay Common
Home-page: https://www.bsc.es/research-and-development/software-and-apps/software-list/dataclay
Project-URL: Bug Tracker, https://www.bsc.es/research-and-development/software-and-apps/software-list/dataclay
Requires-Python: >=3.6
Requires-Dist: grpcio
